digestify/__init__.py
digestify/client.py
digestify/models.py
digestify/py.typed
digestify/settings.py
digestify-0.1.2.dist-info/WHEEL
digestify-0.1.2.dist-info/METADATA
digestify-0.1.2.dist-info/RECORD
