Metadata-Version: 2.4
Name: digestify
Version: 0.1.2
Summary: Digestify is a Python library that generates comprehensive news digests and content summaries for specific topics using OpenAI and the WebQuest MCP server.
License-Expression: Apache-2.0
Requires-Dist: openai>=2.9.0
Requires-Dist: pydantic>=2.12.4
Requires-Dist: pydantic-settings>=2.12.0
Requires-Python: >=3.12
Project-URL: Source, https://github.com/mustafametesengul/digestify
